{"moving":{"yaw_mod_opt":1,"fake_flick":false,"yaw_opt":4,"roll":false,"rollint_r":0,"fake_l":58,"random_lean":false,"lby_l":58,"fake_flick_angle":0,"fake_r":58,"ticks_to_flick":0,"yaw_mod_add":35,"max_velo_int":100,"rollint_l":0,"random_desync":false,"yaw_add":0,"lby_r":58,"fake_opt":0},"slowwalk":{"yaw_mod_opt":0,"fake_flick":false,"yaw_opt":4,"roll":true,"rollint_r":90,"fake_l":56,"random_lean":false,"lby_l":58,"fake_flick_angle":0,"fake_r":58,"ticks_to_flick":0,"yaw_mod_add":0,"max_velo_int":100,"rollint_l":90,"random_desync":false,"yaw_add":20,"lby_r":58,"fake_opt":0},"air":{"yaw_mod_opt":1,"fake_flick":false,"yaw_opt":4,"roll":false,"rollint_r":0,"fake_l":58,"random_lean":false,"lby_l":58,"fake_flick_angle":0,"fake_r":58,"ticks_to_flick":0,"yaw_mod_add":64,"max_velo_int":100,"rollint_l":0,"random_desync":false,"yaw_add":0,"lby_r":58,"fake_opt":2},"standing":{"yaw_mod_opt":0,"fake_flick":false,"yaw_opt":4,"roll":true,"rollint_r":90,"fake_l":58,"random_lean":false,"lby_l":58,"fake_flick_angle":0,"fake_r":58,"ticks_to_flick":0,"yaw_mod_add":0,"max_velo_int":100,"rollint_l":90,"random_desync":false,"yaw_add":23,"lby_r":58,"fake_opt":0}}
